requirements.txt
setup.py
django_configurations_ec2/__init__.py
django_configurations_ec2.egg-info/PKG-INFO
django_configurations_ec2.egg-info/SOURCES.txt
django_configurations_ec2.egg-info/dependency_links.txt
django_configurations_ec2.egg-info/requires.txt
django_configurations_ec2.egg-info/top_level.txt