Metadata-Version: 2.1
Name: django-configurations-ec2
Version: 2020.7.1
Summary: django-configurations AWS EC2 settings
Home-page: https://github.com/andrewp-as-is/django-configurations-ec2.py
License: Unlicense
Keywords: django django-configurations AWS EC2
Platform: UNKNOWN
Classifier: Framework :: Django
Classifier: License :: Public Domain
Classifier: Operating System :: OS Independent
Classifier: Programming Language :: Python :: 3
